Metadata-Version: 2.1
Name: no-teg
Version: 0.2.1
Summary: A quick and easy tournament manager
Author-email: Aaron Ashery <aaron.ashery1@gmail.com>
License:                                  Apache License
Project-URL: repository, https://github.com/AaronAshery/no-teg
Classifier: Development Status :: 2 - Pre-Alpha
Classifier: Programming Language :: Python :: Implementation :: CPython
Classifier: Programming Language :: Python :: Implementation :: PyPy
Classifier: Programming Language :: Python :: 3
Classifier: Programming Language :: Python :: 3.7
Classifier: Programming Language :: Python :: 3.8
Classifier: Programming Language :: Python :: 3.9
Classifier: Programming Language :: Python :: 3.10
Classifier: Programming Language :: Python :: 3.11
Requires-Python: >=3.7
Provides-Extra: develop
License-File: LICENSE
